setup.py
edssdk/__init__.py
edssdk/edsCluster.py
edssdk/edsConfig.py
edssdk.egg-info/PKG-INFO
edssdk.egg-info/SOURCES.txt
edssdk.egg-info/dependency_links.txt
edssdk.egg-info/requires.txt
edssdk.egg-info/top_level.txt