Metadata-Version: 1.0
Name: edssdk
Version: 0.4.4
Summary: eds sdk
Home-page: http://www.xiaoh.me
Author: xiaoh
Author-email: huoxingming@gmail.com
License: MIT Licence
Keywords: pip,ehc,datacanvas,eds,xiaoh
Platform: any
